pycdp/__init__.py
pycdp/asyncio.py
pycdp/base.py
pycdp/browser.py
pycdp/cdp/README.md
pycdp/cdp/__init__.py
pycdp/cdp/accessibility.py
pycdp/cdp/animation.py
pycdp/cdp/audits.py
pycdp/cdp/autofill.py
pycdp/cdp/background_service.py
pycdp/cdp/browser.py
pycdp/cdp/cache_storage.py
pycdp/cdp/cast.py
pycdp/cdp/console.py
pycdp/cdp/css.py
pycdp/cdp/database.py
pycdp/cdp/debugger.py
pycdp/cdp/device_access.py
pycdp/cdp/device_orientation.py
pycdp/cdp/dom.py
pycdp/cdp/dom_debugger.py
pycdp/cdp/dom_snapshot.py
pycdp/cdp/dom_storage.py
pycdp/cdp/emulation.py
pycdp/cdp/event_breakpoints.py
pycdp/cdp/fed_cm.py
pycdp/cdp/fetch.py
pycdp/cdp/headless_experimental.py
pycdp/cdp/heap_profiler.py
pycdp/cdp/indexed_db.py
pycdp/cdp/input_.py
pycdp/cdp/inspector.py
pycdp/cdp/io.py
pycdp/cdp/layer_tree.py
pycdp/cdp/log.py
pycdp/cdp/media.py
pycdp/cdp/memory.py
pycdp/cdp/network.py
pycdp/cdp/overlay.py
pycdp/cdp/page.py
pycdp/cdp/performance.py
pycdp/cdp/performance_timeline.py
pycdp/cdp/preload.py
pycdp/cdp/profiler.py
pycdp/cdp/py.typed
pycdp/cdp/runtime.py
pycdp/cdp/schema.py
pycdp/cdp/security.py
pycdp/cdp/service_worker.py
pycdp/cdp/storage.py
pycdp/cdp/system_info.py
pycdp/cdp/target.py
pycdp/cdp/tethering.py
pycdp/cdp/tracing.py
pycdp/cdp/util.py
pycdp/cdp/web_audio.py
pycdp/cdp/web_authn.py
pycdp/exceptions.py
pycdp/gen/README.md
pycdp/gen/__init__.py
pycdp/gen/browser_protocol.json
pycdp/gen/generate.py
pycdp/gen/js_protocol.json
pycdp/gen/test_generate.py
pycdp/twisted.py
pycdp/utils.py
python_recentx-1.4.2.dist-info/LICENSE
python_recentx-1.4.2.dist-info/METADATA
python_recentx-1.4.2.dist-info/WHEEL
python_recentx-1.4.2.dist-info/entry_points.txt
python_recentx-1.4.2.dist-info/RECORD
