Metadata-Version: 2.1
Name: python-recentx
Version: 1.4.2
Summary: Python type wrappers for Chrome DevTools Protocol (CDP)
Home-page: https://github.com/HMaker/python-recentx
License: MIT
Author: Mark E. Haase
Author-email: mehaase@gmail.com
Requires-Python: >=3.8,<4.0
Classifier: Development Status :: 3 - Alpha
Classifier: Intended Audience :: Developers
Classifier: License :: OSI Approved :: MIT License
Classifier: Programming Language :: Python :: 3
Classifier: Programming Language :: Python :: 3.8
Classifier: Programming Language :: Python :: 3.9
Classifier: Programming Language :: Python :: 3.10
Classifier: Programming Language :: Python :: 3.11
Classifier: Programming Language :: Python :: 3.12
Classifier: Programming Language :: Python :: 3 :: Only
Classifier: Topic :: Internet
Requires-Dist: deprecated (==1.2.9)
Requires-Dist: inflection (==0.4.0)
